{
    "status": 200,
    "message": "Question Data fetched successfully",
    "data": {
        "question": {
            "questionFrontendId": 703778,
            "title": "Check if a Integer is power of 8 or not",
            "titleSlug": "check-if-a-integer-is-power-of-8-or-not2537",
            "content": "<p><span style=\"font-size:18px\">Given a positive integer N, The task is to find if it is a power of eight or not.</span></p>\n\n<p><span style=\"font-size:18px\"><strong>Example 1:</strong>&nbsp;</span></p>\n\n<pre>\n<span style=\"font-size:18px\"><strong>Input: </strong>64\n<strong>Output: </strong>Yes\n<strong>Explanation: </strong>64 is power of 8.</span>\n</pre>\n\n<p><span style=\"font-size:18px\"><strong>Example 2:</strong></span></p>\n\n<pre>\n<span style=\"font-size:18px\"><strong>Input: </strong>75\n<strong>Output: </strong>No\n<strong>Explanation: </strong>75 is not a power of 8.</span>\n\n</pre>\n\n<p><span style=\"font-size:18px\"><strong>Your Task:</strong></span><br />\n<span style=\"font-size:18px\">You don&#39;t need to read or print anything. your task is to complete the function&nbsp;<strong>is_power_of_eight()&nbsp;</strong>which takes N as the input parameter and returns &quot;Yes&quot; if N is power of eight otherwise returns &quot;No&quot;(Wihtout quotes).</span></p>\n\n<p><span style=\"font-size:18px\"><strong>Expected Time Complexity:&nbsp;</strong>O(log(N))<br />\n<strong>Expected Space Complexity:&nbsp;</strong>O(1)</span></p>\n\n<p><span style=\"font-size:18px\"><strong>Constraints:</strong><br />\n1 &lt;= N &lt;= 10<sup>18</sup></span></p>\n",
            "isPaidOnly": false,
            "difficulty": "Easy",
            "likes": "NA",
            "dislikes": "NA",
            "rephrased": {
                "body": "Given a positive integer N, determine if it is a power of eight.",
                "constraints": [
                    "1 <= N <= 10^18"
                ],
                "testcases": [
                    {
                        "input": "64",
                        "output": "Yes",
                        "explanation": "64 is 8 raised to the power of 2 (8^2 = 64)."
                    },
                    {
                        "input": "75",
                        "output": "No",
                        "explanation": "75 cannot be expressed as 8 raised to any integer power."
                    }
                ]
            }
        },
        "similar": [],
        "hints": [
            "<p><span style=\"font-size:18px\">Find x where 2<sup>3x = N</sup></span></p>"
        ],
        "relatedTopics": [
            {
                "name": "Bit Magic",
                "slug": "bit-magic"
            },
            {
                "name": "Data Structures",
                "slug": "data-structures"
            }
        ],
        "companies": [],
        "solutions": {
            "cpp": {
                "lang": "C++",
                "full_func": "\nclass Solution {\npublic:\n    string is_power_of_eight(long long int n ) \n    {\n    \tint x = log2(n);\n    \tif(x % 3 == 0 and (1LL << x) == n)\n    \t\treturn \"Yes\";\n    \treturn \"No\";\n    }\n};\n",
                "lang_text": "cpp"
            },
            "java": {
                "lang": "Java",
                "full_func": null,
                "lang_text": "java"
            },
            "py": {
                "lang": "Python",
                "full_func": null,
                "lang_text": "py"
            }
        },
        "platform": "GFG"
    }
}