{
    "status": 200,
    "message": "Question Data fetched successfully",
    "data": {
        "question": {
            "questionFrontendId": 879282,
            "title": "Print ascii value in python",
            "titleSlug": "print-ascii-value-in-python",
            "content": "<p><span >Given a character <strong>ch&nbsp;</strong>as input, print its ascii value.</span></p>\n<p><span ><strong>Examples:</strong></span></p>\n<pre><span >Input: ch = 'a'</span><br /><span >Output: 97</span></pre>\n<pre><span >Input: ch = 'A'</span><br /><span >Output: 65</span></pre>",
            "isPaidOnly": false,
            "difficulty": "Easy",
            "likes": "NA",
            "dislikes": "NA",
            "rephrased": {
                "body": "Write a program that takes a single character as input and prints its ASCII (American Standard Code for Information Interchange) value.",
                "constraints": [],
                "testcases": [
                    {
                        "input": "a",
                        "output": "97",
                        "explanation": "The ASCII value of the character 'a' is 97."
                    },
                    {
                        "input": "A",
                        "output": "65",
                        "explanation": "The ASCII value of the character 'A' is 65."
                    }
                ]
            }
        },
        "similar": [],
        "hints": [
            "<p>Use ord(ch) to get character's ascii value</p>"
        ],
        "relatedTopics": [],
        "companies": [],
        "solutions": [
            {
                "lang": "Python3",
                "full_func": "#Back-end complete function Template for Python 3\nclass Solution:\n\n    def printAscii(self, ch):\n        ascii = ord(ch)\n        print(ascii)\n",
                "lang_text": "python3"
            }
        ],
        "platform": "GFG"
    }
}