{
    "status": 200,
    "message": "Question Data fetched successfully",
    "data": {
        "question": {
            "questionFrontendId": 705567,
            "title": "Print Pattern",
            "titleSlug": "print-pattern3549",
            "content": "<p><span style=\"font-size: 14pt; font-family: 'andale mono', monospace;\"><span style=\"color: rgba(0, 0, 0, 0.87); background-color: #ffffff;\">Print a sequence of numbers starting with&nbsp;</span><span style=\"box-sizing: inherit; font-weight: bolder; color: rgba(0, 0, 0, 0.87); background-color: #ffffff;\"><span class=\"katex\" style=\"box-sizing: inherit;\">n</span></span><span style=\"color: rgba(0, 0, 0, 0.87); background-color: #ffffff;\">, without using a loop. Replace&nbsp;</span><span style=\"box-sizing: inherit; font-weight: bolder; color: rgba(0, 0, 0, 0.87); background-color: #ffffff;\"><span class=\"katex\" style=\"box-sizing: inherit;\">n</span></span><span style=\"color: rgba(0, 0, 0, 0.87); background-color: #ffffff;\">&nbsp;with&nbsp;</span><span class=\"katex\" style=\"box-sizing: inherit; color: rgba(0, 0, 0, 0.87); background-color: #ffffff;\"><span class=\"katex-mathml\" style=\"box-sizing: inherit;\">n - 5,&nbsp;</span><span class=\"katex-html\" style=\"box-sizing: inherit;\" aria-hidden=\"true\"><span class=\"base\" style=\"box-sizing: inherit;\"><span class=\"mord mathnormal\" style=\"box-sizing: inherit;\">n</span><span class=\"mbin\" style=\"box-sizing: inherit;\">&minus;</span></span><span class=\"base\" style=\"box-sizing: inherit;\"><span class=\"mord\" style=\"box-sizing: inherit;\">5...</span></span></span></span><span style=\"color: rgba(0, 0, 0, 0.87); background-color: #ffffff;\">&nbsp;until&nbsp;</span><span class=\"katex\" style=\"box-sizing: inherit; color: rgba(0, 0, 0, 0.87); background-color: #ffffff;\"><span class=\"katex-mathml\" style=\"box-sizing: inherit;\">n&le;0</span></span><span style=\"color: rgba(0, 0, 0, 0.87); background-color: #ffffff;\">. Then, replace&nbsp;</span><span class=\"katex\" style=\"box-sizing: inherit; color: rgba(0, 0, 0, 0.87); background-color: #ffffff;\"><span class=\"katex-html\" style=\"box-sizing: inherit;\" aria-hidden=\"true\">n</span></span><span style=\"color: rgba(0, 0, 0, 0.87); background-color: #ffffff;\">&nbsp;with&nbsp;</span><span class=\"katex\" style=\"box-sizing: inherit; color: rgba(0, 0, 0, 0.87); background-color: #ffffff;\"><span class=\"katex-mathml\" style=\"box-sizing: inherit;\">n+5, n + 5,&nbsp;</span><span class=\"katex-html\" style=\"box-sizing: inherit;\" aria-hidden=\"true\"><span class=\"base\" style=\"box-sizing: inherit;\"><span class=\"mord mathnormal\" style=\"box-sizing: inherit;\">n</span><span class=\"mbin\" style=\"box-sizing: inherit;\">+</span></span><span class=\"base\" style=\"box-sizing: inherit;\"><span class=\"mord\" style=\"box-sizing: inherit;\">5</span></span></span></span><span style=\"color: rgba(0, 0, 0, 0.87); background-color: #ffffff;\">&nbsp;until&nbsp;</span><span style=\"box-sizing: inherit; font-weight: bolder; color: rgba(0, 0, 0, 0.87); background-color: #ffffff;\"><span class=\"katex\" style=\"box-sizing: inherit;\">n</span></span><span style=\"color: rgba(0, 0, 0, 0.87); background-color: #ffffff;\">&nbsp;regains its initial value. Complete the function&nbsp;</span><code style=\"box-sizing: inherit; color: rgba(0, 0, 0, 0.87); background-color: #ffffff;\">pattern(n)</code><span style=\"color: rgba(0, 0, 0, 0.87); background-color: #ffffff;\">&nbsp;which takes&nbsp;</span><span class=\"katex\" style=\"box-sizing: inherit; color: rgba(0, 0, 0, 0.87); background-color: #ffffff;\"><span class=\"katex-html\" style=\"box-sizing: inherit;\" aria-hidden=\"true\">n</span></span><span style=\"color: rgba(0, 0, 0, 0.87); background-color: #ffffff;\">&nbsp;as input and returns a list containing the pattern.</span></span></p>\n<p><strong><span style=\"font-size: 18px;\">Examples<br /></span></strong></p>\n<pre><span style=\"font-size: 18px;\"><strong>Input:</strong> n = 16\n<strong>Output:</strong> 16 11 6 1 -4 1 6 11 16\n<strong>Explanation:</strong> The value decreases until it is greater than 0. After that it increases and stops when it becomes 16 again.</span></pre>\n<pre><span style=\"font-size: 18px;\"><strong>Input:</strong> n = 10\n<strong>Output: </strong>10 5 0 5 10\n<strong>Explanation:</strong> It follows the same logic as per the above example.</span></pre>\n<p><span style=\"font-size: 18px;\"><strong>Expected Time Complexity:</strong> O(n)<br /><strong>Expected Auxiliary Space:</strong> O(n)</span></p>\n<p><span style=\"font-size: 18px;\"><strong>Constraints:</strong><br />-10<sup>5</sup> &le; n &le; 10<sup>5</sup></span></p>",
            "isPaidOnly": false,
            "difficulty": "Easy",
            "likes": "NA",
            "dislikes": "NA",
            "rephrased": {
                "body": "Given a number 'n', generate a sequence of numbers without using loops.  The sequence should start with 'n' and repeatedly subtract 5 until the number is less than or equal to 0. After this point, the sequence should repeatedly add 5 until the number equals the original 'n'.",
                "constraints": [
                    "-10<sup>5</sup> \u2264 n \u2264 10<sup>5</sup>"
                ],
                "testcases": [
                    {
                        "input": "16",
                        "output": "16 11 6 1 -4 1 6 11 16",
                        "explanation": "The sequence starts at 16 and decreases by 5 until -4. Then, it increases by 5 until it reaches the original value of 16."
                    },
                    {
                        "input": "10",
                        "output": "10 5 0 5 10",
                        "explanation": "The sequence begins at 10 and decreases by 5 until 0. Subsequently, it increases by 5 until it equals the original input of 10."
                    }
                ]
            }
        },
        "similar": [],
        "hints": [
            "<p>Try doing with the help of recursion.</p>\n\n<p>Push the value till it is greater than zero and call for (n-4) untill the base condition is reached.</p>"
        ],
        "relatedTopics": [
            {
                "name": "pattern-printing",
                "slug": "pattern-printing"
            },
            {
                "name": "Recursion",
                "slug": "recursion"
            },
            {
                "name": "Algorithms",
                "slug": "algorithms"
            }
        ],
        "companies": [
            "microsoft"
        ],
        "solutions": [
            {
                "lang": "C++",
                "full_func": "// Back-end complete function Template for C++\n\nclass Solution{\npublic:\n    void find_pattern(vector<int>&ans,int curr_val,int N,int pat)\n    {\n        if(pat==1)\n        {\n            ans.push_back(curr_val);\n            if(curr_val>0)\n                find_pattern(ans,curr_val-5,N,pat);\n            else if(curr_val!=N)\n                find_pattern(ans,curr_val+5,N,2);\n        }\n        else\n        {\n            ans.push_back(curr_val);\n            if(curr_val!=N)\n                find_pattern(ans,curr_val+5,N,pat);\n        }\n        return;\n    }\n    \n    vector<int> pattern(int N)\n    {\n        vector<int>ans;\n        int curr_val=N;\n        find_pattern(ans,curr_val,N,1);\n        return ans;\n    }\n};",
                "lang_text": "cpp"
            },
            {
                "lang": "Java",
                "full_func": "class Solution{\n    List<Integer> arr=new ArrayList<>();\n    void f(int curr,int n,int type)\n    {\n        if(curr <= 0)\n            type = 1;\n        \n        arr.add(curr);\n        \n        if(curr==n && type==1)\n            return;\n        \n        if(type == 0)\n            f(curr-5,n,type);\n        else\n            f(curr+5,n,type);\n    }\n    \n    public List<Integer> pattern(int n) {\n        f(n ,n , 0);\n        return arr;\n    }\n}",
                "lang_text": "java"
            },
            {
                "lang": "Python3",
                "full_func": null,
                "lang_text": "python3"
            },
            {
                "lang": "C#",
                "full_func": "//User function Template for C#\n\nclass Solution\n{\n    //Complete this function\n    public List<int> pattern(int N)\n    {\n        List<int> ans = new List<int>();\n        int curr_val = N;\n        find_pattern(ans, curr_val, N, 1);\n        return ans;\n    }\n\n    void find_pattern(List<int> ans, int curr_val, int N, int pat)\n    {\n        if (pat == 1)\n        {\n            ans.Add(curr_val);\n            if (curr_val > 0)\n                find_pattern(ans, curr_val - 5, N, pat);\n            else if (curr_val != N)\n                find_pattern(ans, curr_val + 5, N, 2);\n        }\n        else\n        {\n            ans.Add(curr_val);\n            if (curr_val != N)\n                find_pattern(ans, curr_val + 5, N, pat);\n        }\n        return;\n    }\n}",
                "lang_text": "csharp"
            },
            {
                "lang": "Javascript",
                "full_func": null,
                "lang_text": "javascript"
            }
        ],
        "platform": "GFG"
    }
}