{
    "status": 200,
    "message": "Question Data fetched successfully",
    "data": {
        "question": {
            "questionFrontendId": 700804,
            "title": "While loop- printTable - Java",
            "titleSlug": "while-loop-printtable-java",
            "content": "<p><em><span style=\"font-size: 18px;\">While loop is another loop like for loop but unlike for loop it only checks for one condition.<br /></span></em><span style=\"font-size: 18px;\">Here, we will use<strong>&nbsp;</strong>a<strong> while loop</strong> and print a number<strong> n's table in reverse order.</strong></span></p>\n<p><span style=\"font-size: 18px;\"><strong>Examples:</strong></span></p>\n<pre><span style=\"font-size: 18px;\"><strong>Input: </strong>n =<strong> </strong>1</span>\n<span style=\"font-size: 18px;\"><strong><span style=\"font-size: 18px;\">Output:</span> </strong></span><span style=\"font-size: 18px;\">10 9 8 7 6 5 4 3 2 1</span></pre>\n<pre><span style=\"font-size: 18px;\"><strong>Input: </strong>n =<strong> </strong>2</span>\n<span style=\"font-size: 18px;\"><strong>Output: </strong></span><span style=\"font-size: 18px;\">20 18 16 14 12 10 8 6 4 2</span></pre>\n<p><span style=\"font-size: 18px;\"><strong>Constraints:</strong><br />1 &lt;= n&lt;= 1000</span></p>",
            "isPaidOnly": false,
            "difficulty": "Easy",
            "likes": "NA",
            "dislikes": "NA",
            "rephrased": {
                "body": "Write a program that uses a `while` loop to print the multiplication table of a given number `n` in reverse order, from n*10 down to n*1.",
                "constraints": [
                    "1 <= n <= 1000"
                ],
                "testcases": [
                    {
                        "input": "1",
                        "output": "10 9 8 7 6 5 4 3 2 1",
                        "explanation": null
                    },
                    {
                        "input": "2",
                        "output": "20 18 16 14 12 10 8 6 4 2",
                        "explanation": null
                    }
                ]
            }
        },
        "similar": [],
        "hints": [
            "<p>Multiply value with 10 and decrease accordingly.</p>"
        ],
        "relatedTopics": [
            {
                "name": "Java-Control-Flow",
                "slug": "java-control-flow"
            }
        ],
        "companies": [],
        "solutions": {
            "java": {
                "lang": "Java",
                "full_func": "//Back-end complete function Template for Java\nimport java.util.*;\n\nclass Solution {\n    public void calculateMultiples(int n) {\n        int multiplier = 10;\n        while (multiplier > 0) {\n            int ans = n * multiplier;\n            System.out.print(ans + \" \");\n            multiplier--;\n        }\n        System.out.println();\n    }\n}",
                "lang_text": "java"
            }
        },
        "platform": "GFG"
    }
}