{
    "status": 200,
    "message": "Question Data fetched successfully",
    "data": {
        "question": {
            "questionFrontendId": 8641,
            "title": "Find power of a number",
            "titleSlug": "find-power-of-a-number_893198",
            "content": "<h4 id=\"ninja-is-sitting-in-an-examination-hall-he-is-encountered-with-a-problem-statement-find-x-to-the-power-n-i-e-x-n-where-x-and-n-are-two-integers\">Ninja is sitting in an examination hall. He is encountered with a problem statement, &quot;Find \u2018X\u2019 to the power \u2018N\u2019 (i.e. \u2018X\u2019 ^ \u2018N\u2019). Where \u2018X\u2019 and \u2018N\u2019 are two integers.&quot;</h4>\n\n<h4 id=\"ninja-was-not-prepared-for-this-question-at-all-as-this-question-was-unexpected-in-the-exam\">Ninja was not prepared for this question at all, as this question was unexpected in the exam.</h4>\n\n<h4 id=\"he-is-asking-for-your-help-to-solve-this-problem-help-ninja-to-find-the-answer-to-the-problem\">He is asking for your help to solve this problem. Help Ninja to find the answer to the problem.</h4>\n\n<h4 id=\"note\">Note :</h4>\n\n<pre><code>For this question, you can assume that 0 raised to the power of 0 is 1.\n</code></pre>\n\n<h4 id=\"input-format\">Input format :</h4>\n\n<pre><code>The first line of input contains integer \u2018T\u2019 denoting the number of test cases. Then each test case follows:\n\nThe first and only line of each test case contains two integers \u2018X\u2019 and \u2018N\u2019 (separated by space).\n</code></pre>\n\n<h4 id=\"output-format\">Output Format :</h4>\n\n<pre><code>Output will contain a single integer which will be equal to X ^ N (i.e. X raise to the power N).\n\nOutput of each test cases will be printed on separate line.\n</code></pre>\n\n<h4 id=\"note\">Note:</h4>\n\n<pre><code>You do not need to print anything, it has already been taken care of. Just implement the given function.\n</code></pre>\n\n<h4 id=\"constraints\">Constraints:</h4>\n\n<pre><code>1 &lt;= T &lt;= 5\n0 &lt;= X &lt;= 10\n0 &lt;= N &lt;= 10\n\nTime Limit: 1 sec.\n</code></pre>\n<h5 id=\"sample-input-1\">Sample Input 1:</h5>\n\n<pre><code>2\n5 2\n9 3\n</code></pre>\n\n<h5 id=\"sample-output-1\">Sample Output 1:</h5>\n\n<pre><code>25\n729\n</code></pre>\n\n<h5 id=\"explanation-for-sample-input-1\">Explanation for Sample Input 1:</h5>\n\n<pre><code>Test Case 1: \nGiven X = 5 and N = 2. So, 5 ^ 2 = 25. As 5 * 5 = 25.\n\nTest Case 2:\nGiven X = 9 and N = 3. So, 9 ^ 3 = 729. As 9 * 9 * 9 = 729.\n</code></pre>\n\n<h5 id=\"sample-input-2\">Sample Input 2:</h5>\n\n<pre><code>2\n5 0\n1 10\n</code></pre>\n\n<h5 id=\"sample-output-2\">Sample Output 2:</h5>\n\n<pre><code>1\n1\n</code></pre>\n",
            "isPaidOnly": false,
            "difficulty": "Easy",
            "likes": 67,
            "dislikes": "NA",
            "rephrased": {
                "body": "Ninja is taking an exam and needs help calculating X raised to the power of N (X^N), where X and N are integers.  You are tasked with writing a function that efficiently computes X^N, given the constraints.  Assume 0^0 = 1.",
                "constraints": [
                    "1 <= T <= 5",
                    "0 <= X <= 10",
                    "0 <= N <= 10",
                    "Time Limit: 1 sec."
                ],
                "testcases": [
                    {
                        "input": "5 2",
                        "output": "25",
                        "explanation": "X = 5 and N = 2.  Therefore, 5^2 = 5 * 5 = 25."
                    },
                    {
                        "input": "9 3",
                        "output": "729",
                        "explanation": "X = 9 and N = 3. Therefore, 9^3 = 9 * 9 * 9 = 729."
                    },
                    {
                        "input": "5 0",
                        "output": "1",
                        "explanation": "X = 5 and N = 0. Any number raised to the power of 0 is 1. According to the problem statment, 0^0 = 1."
                    },
                    {
                        "input": "1 10",
                        "output": "1",
                        "explanation": "X = 1 and N = 10. 1 raised to any power is always 1."
                    }
                ]
            }
        },
        "similar": [],
        "hints": [
            "<p>Think of a recursive Approach.</p>",
            "<p>Think of optimizing the previous recursive approach in terms of time complexity.</p>"
        ],
        "relatedTopics": [],
        "solutions": [],
        "platform": "CODESTUDIO"
    }
}