{
    "status": 200,
    "message": "Question Data fetched successfully",
    "data": {
        "question": {
            "questionFrontendId": 19907,
            "title": "First N",
            "titleSlug": "first-n_4605104",
            "content": "<h4 id=\"you-are-given-a-positive-integer-n-you-have-to-find-the-sum-of-first-n-natural-numbers\">You are given a positive integer \u2018N\u2019. You have to find the sum of first \u2018N\u2019 natural numbers.</h4>\n\n<p></br></p>\n\n<h5 id=\"for-example\">For Example:</h5>\n\n<pre><code>If N = 3.\nSum of the first 3 natural numbers will be 1 + 2 + 3 = 6. Hence, the output will be 6.\n</code></pre>\n\n<h5 id=\"input-format\">Input Format :</h5>\n\n<pre><code>The first line of the input contains an integer, &#39;T\u2019, denoting the number of test cases.\n\nThe first line of each test case contains a single positive integer \u2018N\u2019.\n</code></pre>\n\n<h5 id=\"output-format\">Output Format :</h5>\n\n<pre><code>For each test case, print the sum of first \u2018N\u2019 natural numbers.\n\nPrint a separate line for each test case.\n</code></pre>\n\n<h5 id=\"note\">Note :</h5>\n\n<pre><code>You do not need to print anything, it has already been taken care of. Just implement the given function.\n</code></pre>\n\n<h5 id=\"constraints\">Constraints :</h5>\n\n<pre><code>1 &lt;= T &lt;= 10\n1 &lt;= N &lt;= 10^6\n\nTime limit: 1 sec\n</code></pre>\n<h5 id=\"sample-input-1\">Sample Input 1 :</h5>\n\n<pre><code>2\n3\n2\n</code></pre>\n\n<h5 id=\"sample-output-1\">Sample output 1 :</h5>\n\n<pre><code>6\n3\n</code></pre>\n\n<h5 id=\"explanation-for-sample-output-1\">Explanation For Sample Output 1 :</h5>\n\n<pre><code>For the first test case,\nN = 3.\nSum of the first 3 natural numbers will be 1 + 2 + 3 = 6. Hence, the output will be 6.\n\nFor the second test case,\nN = 2.\nSum of the first 2 natural numbers will be 1 + 2 = 3. Hence, the output will be 3.\n</code></pre>\n\n<h5 id=\"sample-input-2\">Sample Input 2 :</h5>\n\n<pre><code>2\n1\n4\n</code></pre>\n\n<h5 id=\"sample-output-2\">Sample output 2 :</h5>\n\n<pre><code>1\n10\n</code></pre>\n",
            "isPaidOnly": false,
            "difficulty": "Easy",
            "likes": 0,
            "dislikes": "NA",
            "rephrased": {
                "body": "Given a positive integer 'n', calculate and return the sum of the first 'n' natural numbers (1, 2, 3, ..., n).",
                "constraints": [
                    "1 <= T <= 10",
                    "1 <= N <= 10^6",
                    "Time limit: 1 sec"
                ],
                "testcases": [
                    {
                        "input": "n = 3",
                        "output": "6",
                        "explanation": "The sum of the first 3 natural numbers (1 + 2 + 3) is 6."
                    },
                    {
                        "input": "n = 2",
                        "output": "3",
                        "explanation": "The sum of the first 2 natural numbers (1 + 2) is 3."
                    },
                    {
                        "input": "n = 1",
                        "output": "1",
                        "explanation": "The sum of the first 1 natural number (1) is 1."
                    },
                    {
                        "input": "n = 4",
                        "output": "10",
                        "explanation": "The sum of the first 4 natural numbers (1 + 2 + 3 + 4) is 10."
                    },
                    {
                        "input": "n = 10",
                        "output": "55",
                        "explanation": "The sum of the first 10 natural numbers (1 + 2 + 3 + 4 + 5 + 6 + 7 + 8 + 9 + 10) is 55."
                    }
                ]
            }
        },
        "similar": [],
        "hints": [
            "<p>Run a loop from 1 to \u2018N\u2019 and find the sum.</p>",
            "<p>Sequence from 1 to \u2018N\u2019 is in Arithmetic progression.</p>"
        ],
        "relatedTopics": [
            {
                "name": "Math",
                "slug": "math"
            }
        ],
        "solutions": {},
        "platform": "CODESTUDIO"
    }
}