{
    "status": 200,
    "message": "Question Data fetched successfully",
    "data": {
        "question": {
            "questionFrontendId": 20033,
            "title": "Radix Sort",
            "titleSlug": "radix-sort_4605994",
            "content": "<h4 id=\"ninja-is-given-an-array-of-integers-arr-of-size-n-he-has-to-sort-the-given-array-in-increasing-order-using-radix-sort\">Ninja is given an array of integers \u2018ARR\u2019 of size \u2018N\u2019. He has to sort the given array in increasing order using radix sort.</h4>\n\n<h4 id=\"ninja-called-you-for-help-as-you-are-his-only-friend-help-him-to-solve-the-problem\">Ninja called you for help as you are his only friend. Help him to solve the problem.</h4>\n\n<h5 id=\"example\">Example :</h5>\n\n<pre><code>Input: \u2018N\u2019 = \u20184\u2019 ,  &#39;V&#39; = [ 2 , 1 , 4 , 3 ] \n\nOutput: &quot;1 2 3 4&quot;\n\nAs [ 1 , 2 , 3 , 4 ] is the sorted order.\n</code></pre>\n\n<h5 id=\"input-format\">Input Format :</h5>\n\n<pre><code>The first line will contain the integer &#39;T&#39;, denoting the number of test cases.\n\nFor each test case, the first line contains a single integer \u2018N\u2019 the size of the input array.\n\nSecond-line contains \u2018N\u2019 space-separated integers which are the elements of the input array.\n</code></pre>\n\n<h5 id=\"output-format\">Output format :</h5>\n\n<pre><code>For each test case, print the element of the array input array in increasing order.\n</code></pre>\n\n<h5 id=\"note\">Note :</h5>\n\n<pre><code>You don&#39;t need to print anything. It has already been taken care of. Just implement the given function.\n</code></pre>\n\n<h5 id=\"constraints\">Constraints :</h5>\n\n<pre><code>1 &lt;= &#39;T&#39; &lt;= 10\n1 &lt;= \u2018N\u2019 &lt;= 10^4\n1 &lt;= ARR[i] &lt;= 10^9\nTime Limit: 1 sec\n</code></pre>\n<h5 id=\"sample-input-1\">Sample Input 1 :</h5>\n\n<pre><code>2\n4\n1 4 3 5\n5 \n5 4 3 2 1\n</code></pre>\n\n<h5 id=\"sample-output-1\">Sample Output 1 :</h5>\n\n<pre><code>1 3 4 5\n1 2 3 4 5\n</code></pre>\n\n<h5 id=\"explanation-of-sample-input-1\">Explanation Of Sample Input 1 :</h5>\n\n<pre><code>In test case \u20181\u2019, \u20181 3 4 5\u2019 is the increasing sorted order.\nIn test case \u20182\u2019. \u20181 2 3 4 5\u2019 is the increasing sorted order.\n</code></pre>\n\n<h5 id=\"sample-input-2\">Sample Input 2 :</h5>\n\n<pre><code>2\n2\n30 25\n6 \n2 2 2 2 2 2\n</code></pre>\n\n<h5 id=\"sample-output-2\">Sample Output 2 :</h5>\n\n<pre><code>25 30\n2 2 2 2 2 2\n</code></pre>\n",
            "isPaidOnly": false,
            "difficulty": "Medium",
            "likes": 1,
            "dislikes": "NA",
            "rephrased": {
                "body": "Implement the `radixSort` function to sort an array of integers in increasing order using the Radix Sort algorithm. You are given the size of the array 'N' and the array 'ARR' itself.",
                "constraints": [
                    "1 <= N <= 10^4",
                    "1 <= ARR[i] <= 10^9",
                    "Time Limit: 1 sec"
                ],
                "testcases": [
                    {
                        "input": "n = 4, arr = [2, 1, 4, 3]",
                        "output": "[1, 2, 3, 4]",
                        "explanation": "The sorted order of the input array [2, 1, 4, 3] is [1, 2, 3, 4]."
                    },
                    {
                        "input": "n = 5, arr = [5, 4, 3, 2, 1]",
                        "output": "[1, 2, 3, 4, 5]",
                        "explanation": "The sorted order of the input array [5, 4, 3, 2, 1] is [1, 2, 3, 4, 5]."
                    },
                    {
                        "input": "n = 2, arr = [30, 25]",
                        "output": "[25, 30]",
                        "explanation": "The sorted order of the input array [30, 25] is [25, 30]."
                    },
                    {
                        "input": "n = 6, arr = [2, 2, 2, 2, 2, 2]",
                        "output": "[2, 2, 2, 2, 2, 2]",
                        "explanation": "The input array [2, 2, 2, 2, 2, 2] is already sorted, so the output remains the same."
                    },
                    {
                        "input": "n = 3, arr = [10, 1, 100]",
                        "output": "[1, 10, 100]",
                        "explanation": "The sorted order of the input array [10, 1, 100] is [1, 10, 100]."
                    }
                ]
            }
        },
        "similar": [],
        "hints": [
            "<p><strong>&nbsp;</strong>What happens in the counting sort?</p>",
            "<p>What if the elements are not in the range from 1 to \u2018N\u2019 in counting sort they are too big?</p>"
        ],
        "relatedTopics": [
            {
                "name": "Sorting",
                "slug": "sorting"
            }
        ],
        "solutions": {},
        "platform": "CODESTUDIO"
    }
}