{
    "status": 200,
    "message": "Question Data fetched successfully",
    "data": {
        "question": {
            "questionFrontendId": 9294,
            "title": "Spiral Matrix",
            "titleSlug": "spiral-matrix_982761",
            "content": "<h4 id=\"you-are-given-a-n-x-m-matrix-of-integers-print-the-spiral-path-of-the-matrix\">You are given a N x M matrix of integers, print the spiral path of the matrix.</h4>\n\n<h4 id=\"for-example\">For example:</h4>\n\n<p><img src=\"https://files.codingninjas.in/image1-5402.png\" alt=\"Spiral Path\"></p>\n\n<h5 id=\"input-format\">Input Format:</h5>\n\n<pre><code>The first line contains an integer &#39;T&#39; which denotes the number of test cases or queries to be run. Then the test cases follow.\n\nThe first line of each test case contains two single space-separated integers N and M, denoting the number of rows and columns respectively.\n\nThe next &#39;N&#39; lines, each contains &#39;M&#39; single space-separated integers representing the elements in a row of the matrix.\n</code></pre>\n\n<h5 id=\"output-format\">Output format :</h5>\n\n<pre><code>For each test case/query, print the spiral path of the given matrix.\n\nOutput for every test case will be printed in a separate line.\n</code></pre>\n\n<h5 id=\"note\">Note:</h5>\n\n<pre><code> You do not need to print anything, it has already been taken care of. Just implement the given function.\n</code></pre>\n\n<h5 id=\"constraints\">Constraints:</h5>\n\n<pre><code>1 &lt;= T &lt;= 10\n1 &lt;= N &lt;= 100\n1 &lt;= M &lt;= 100\n-10^9 &lt;= data &lt;= 10^9\n\nwhere \u2018T\u2019 is the number of test cases,  \u2018N\u2019 and \u2018M\u2019 are the numbers of rows and columns respectively and \u2018data\u2019 is the value of the elements of the matrix.\n</code></pre>\n<h5 id=\"sample-input-1\">Sample Input 1 :</h5>\n\n<pre><code>3\n3 6\n1 2 3 4 5 6 \n7 8 9 10 11 12 \n13 14 15 16 17 18\n1 1\n4\n1 5\n1 2 3 4 5\n</code></pre>\n\n<h5 id=\"sample-output-1\">Sample Output 1 :</h5>\n\n<pre><code>1 2 3 4 5 6 12 18 17 16 15 14 13 7 8 9 10 11\n4\n1 2 3 4 5\n</code></pre>\n\n<h5 id=\"explanation-of-the-sample-input-1\">Explanation of the Sample Input 1 :</h5>\n\n<pre><code>The spiral path for test case 1 is as shown below:\n</code></pre>\n\n<p><img src=\"https://files.codingninjas.in/image2-5403.png\" alt=\"Test Case 1\">\n    In the second test case, there is only one element in the matrix, so the spiral path is only that element.\n    In the third test case, there is only one row or 1-D matrix, so the spiral path is only the single traversal of the matrix.</p>\n\n<h5 id=\"sample-input-2\">Sample Input 2 :</h5>\n\n<pre><code>1\n4 4\n1 2 3 4 \n5 6 7 8 \n9 10 11 12 \n13 14 15 16\n</code></pre>\n\n<h5 id=\"sample-output-2\">Sample Output 2 :</h5>\n\n<pre><code>1 2 3 4 8 12 16 15 14 13 9 5 6 7 11 10\n</code></pre>\n",
            "isPaidOnly": false,
            "difficulty": "Easy",
            "likes": 6,
            "dislikes": "NA",
            "rephrased": {
                "body": "Given a 2D matrix of integers with dimensions N x M, traverse and return the elements in a spiral path.",
                "constraints": [
                    "1 <= T <= 10 (Number of test cases)",
                    "1 <= N <= 100 (Number of rows)",
                    "1 <= M <= 100 (Number of columns)",
                    "-10^9 <= data <= 10^9 (Value of matrix elements)"
                ],
                "testcases": [
                    {
                        "input": "matrix=[[1, 2, 3, 4, 5, 6], [7, 8, 9, 10, 11, 12], [13, 14, 15, 16, 17, 18]], n=3, m=6",
                        "output": "1 2 3 4 5 6 12 18 17 16 15 14 13 7 8 9 10 11",
                        "explanation": "The spiral path starts from the top-left corner (1), moves right, then down, then left, then up, and so on, until all elements are visited."
                    },
                    {
                        "input": "matrix=[[4]], n=1, m=1",
                        "output": "4",
                        "explanation": "The matrix has only one element, so the spiral path consists of that single element."
                    },
                    {
                        "input": "matrix=[[1, 2, 3, 4, 5]], n=1, m=5",
                        "output": "1 2 3 4 5",
                        "explanation": "The matrix has only one row, so the spiral path is simply traversing the row from left to right."
                    },
                    {
                        "input": "matrix=[[1, 2, 3, 4], [5, 6, 7, 8], [9, 10, 11, 12], [13, 14, 15, 16]], n=4, m=4",
                        "output": "1 2 3 4 8 12 16 15 14 13 9 5 6 7 11 10",
                        "explanation": "Standard spiral traversal for a 4x4 matrix."
                    }
                ]
            }
        },
        "similar": [],
        "hints": [
            "<p>Print the boundary of the Matrix recursively.</p>",
            "<p>Try to traverse the matrix with the help of loops.</p>",
            "<p>Try to print the spiral path using one loop.</p>"
        ],
        "relatedTopics": [
            {
                "name": "Matrices (2D Arrays)",
                "slug": "matrices-(2d-arrays)"
            }
        ],
        "solutions": {},
        "platform": "CODESTUDIO"
    }
}